tts_middleware/__init__.py
tts_middleware/audio.py
tts_middleware/core.py
tts_middleware/elements.py
tts_middleware-0.4.1.dist-info/WHEEL
tts_middleware-0.4.1.dist-info/METADATA
tts_middleware-0.4.1.dist-info/RECORD
